rulelist/__init__.py
rulelist/rulelist.py
rulelist/datastructure/__init__.py
rulelist/datastructure/data.py
rulelist/datastructure/subgroup.py
rulelist/datastructure/attribute/__init__.py
rulelist/datastructure/attribute/attribute.py
rulelist/datastructure/attribute/nominal_attribute.py
rulelist/datastructure/attribute/numeric_attribute.py
rulelist/mdl/__init__.py
rulelist/mdl/mdl_base_codes.py
rulelist/measures/__init__.py
rulelist/measures/mesaures_classification.py
rulelist/measures/subgroup_measures.py
rulelist/rulelistmodel/__init__.py
rulelist/rulelistmodel/data_encoding.py
rulelist/rulelistmodel/gain_add_rule.py
rulelist/rulelistmodel/model_encoding.py
rulelist/rulelistmodel/prediction.py
rulelist/rulelistmodel/rulesetmodel.py
rulelist/rulelistmodel/statistic.py
rulelist/rulelistmodel/categoricalmodel/__init__.py
rulelist/rulelistmodel/categoricalmodel/categoricalrulelist.py
rulelist/rulelistmodel/categoricalmodel/categoricalstatistic.py
rulelist/rulelistmodel/categoricalmodel/categoricaltarget.py
rulelist/rulelistmodel/categoricalmodel/mdl_categorical.py
rulelist/rulelistmodel/categoricalmodel/prediction_categorical.py
rulelist/rulelistmodel/gaussianmodel/__init__.py
rulelist/rulelistmodel/gaussianmodel/gaussianrulelist.py
rulelist/rulelistmodel/gaussianmodel/gaussianstatistic.py
rulelist/rulelistmodel/gaussianmodel/gaussiantarget.py
rulelist/rulelistmodel/gaussianmodel/mdl_gaussian.py
rulelist/rulelistmodel/gaussianmodel/prediction_gaussian.py
rulelist/search/__init__.py
rulelist/search/iterative_rule_search.py
rulelist/search/beam/__init__.py
rulelist/search/beam/beam.py
rulelist/search/beam/itemset_beamsearch.py
rulelist/search/preminedpatterns/__init__.py
rulelist/util/__init__.py
rulelist/util/bitset_operations.py
rulelist/util/extra_maths.py
rulelist/util/makegraphs.py
rulelist/util/results2folder.py
tests/__init__.py
tests/data/__init__.py
tests/data/test_data.py
tests/mdl/__init__.py
tests/mdl/test_mdl_base_codes.py
tests/rulelistmodel/__init__.py
rulelist-0.2.0.dist-info/LICENSE
rulelist-0.2.0.dist-info/METADATA
rulelist-0.2.0.dist-info/WHEEL
rulelist-0.2.0.dist-info/top_level.txt
rulelist-0.2.0.dist-info/RECORD
