Metadata-Version: 2.1
Name: rulelist
Version: 0.2.0
Summary: Learn rule lists from data for classification, regression or subgroup discovery
Home-page: https://github.com/HMProenca/RuleList
Author: Hugo Proenca
Author-email: hugo.manuel.proenca@gmail.com
License: MIT License
Platform: UNKNOWN
Classifier: Programming Language :: Python :: 3.7
Classifier: Intended Audience :: Developers
Classifier: Intended Audience :: Science/Research
Classifier: License :: OSI Approved
Requires-Python: >=3.7
License-File: LICENSE
Requires-Dist: pytest (>=6.0.1)
Requires-Dist: numpy (>=1.19.1)
Requires-Dist: pandas (>=0.25.3)
Requires-Dist: gmpy2 (>=2.0.8)
Requires-Dist: setuptools (>=50.3.0)
Requires-Dist: typing (>=3.7.4.3)
Requires-Dist: scipy (~=1.5.2)
Requires-Dist: scikit-learn (~=0.23.2)
